slice/__init__.py
slice/image_split.py
slicer_img-2.1.1.dist-info/LICENSE
slicer_img-2.1.1.dist-info/METADATA
slicer_img-2.1.1.dist-info/WHEEL
slicer_img-2.1.1.dist-info/entry_points.txt
slicer_img-2.1.1.dist-info/top_level.txt
slicer_img-2.1.1.dist-info/RECORD
