Metadata-Version: 2.1
Name: slicer-img
Version: 2.1.1
Summary: Slices an image into its constituent parts
Home-page: https://github.com/fl1ghtly/slicer
Author: James Nguyen
License: UNKNOWN
Platform: UNKNOWN
Classifier: Programming Language :: Python :: 3
Classifier: License :: OSI Approved :: MIT License
Classifier: Operating System :: OS Independent
Requires-Python: >=3.6
Requires-Dist: Pillow (>=8.1.1)
